predictramdatalab/__init__.py
predictramdatalab/api.py
predictramdatalab/data_loader.py
predictramdatalab/query_processor - Copy.py
predictramdatalab/query_processor.py
predictramdatalab/utils.py
predictramdatalab/data/all_stocks.json
predictramdatalab-1.0.7.dist-info/METADATA
predictramdatalab-1.0.7.dist-info/WHEEL
predictramdatalab-1.0.7.dist-info/top_level.txt
predictramdatalab-1.0.7.dist-info/RECORD
